Metadata-Version: 2.1
Name: rpatools
Version: 0.1
Summary: Open-source RPA tools
Home-page: UNKNOWN
Author: Kevin Lee
License: UNKNOWN
Platform: UNKNOWN
License-File: LICENSE.txt
